MANIFEST.in
README.md
requirements.pip
setup.py
test-requirements.pip
bin/dk_monitor
data_kennel/__init__.py
data_kennel/config.py
data_kennel/monitor.py
data_kennel/util.py
data_kennel/version.py
data_kennel.egg-info/PKG-INFO
data_kennel.egg-info/SOURCES.txt
data_kennel.egg-info/dependency_links.txt
data_kennel.egg-info/not-zip-safe
data_kennel.egg-info/requires.txt
data_kennel.egg-info/top_level.txt