Metadata-Version: 1.1
Name: data-kennel
Version: 1.0.10
Summary: Data Kennel is a CLI tool for managing Datadog infrastructure.
Home-page: https://github.com/amplify-education/data_kennel
Author: Amplify Education
Author-email: github@amplify.com
License: MIT
Keywords: python,datadog,cli
Platform: UNKNOWN
Classifier: Topic :: Software Development :: Libraries :: Python Modules
Classifier: Programming Language :: Python
Classifier: Programming Language :: Python :: 2
Classifier: Programming Language :: Python :: 2.7
